models/__init__.py
models/adapter.py
models/keyBartPlus.py
KeyBartAdapter-0.1.12.dist-info/LICENSE
KeyBartAdapter-0.1.12.dist-info/METADATA
KeyBartAdapter-0.1.12.dist-info/WHEEL
KeyBartAdapter-0.1.12.dist-info/top_level.txt
KeyBartAdapter-0.1.12.dist-info/RECORD
